jaxson/__init__.py
jaxson/canvas.py
jaxson/utils.py
jaxson-0.1.8.dist-info/WHEEL
jaxson-0.1.8.dist-info/METADATA
jaxson-0.1.8.dist-info/RECORD
